setup.py
bin/avg_light
bin/diffuse_color_light
bin/edge_light
bin/fill_light
bin/object_modifier
bin/regional_light_modifier
bin/soft_light_modifier
light_compositing/__init__.py
light_compositing/basis_lights.py
light_compositing/image_utils.py
light_compositing/light_compositing.py
light_compositing/modifier_lights.py
light_compositing.egg-info/PKG-INFO
light_compositing.egg-info/SOURCES.txt
light_compositing.egg-info/dependency_links.txt
light_compositing.egg-info/requires.txt
light_compositing.egg-info/top_level.txt