Metadata-Version: 1.1
Name: light-compositing
Version: 0.0.1
Summary: An implementation based on the paper: Image Compositing for     Photographic Lighting.
Home-page: https://github.com/tjaartvdwalt/light-compositing
Author: Tjaart van der Walt
Author-email: pypi@tjaart.co.za
License: MIT
Keywords: light compositing
Platform: UNKNOWN
Classifier: Development Status :: 3 - Alpha
Classifier: Topic :: Utilities
